mosaicmap/__init__.py
mosaicmap/core.py
mosaicmap/resources/DejaVuSans.ttf
mosaicmap-0.1.4.dist-info/METADATA
mosaicmap-0.1.4.dist-info/WHEEL
mosaicmap-0.1.4.dist-info/licenses/LICENSE
mosaicmap-0.1.4.dist-info/RECORD
