Metadata-Version: 2.4
Name: mosaicmap
Version: 0.1.4
Summary: A Python library for creating treemaps with images
Project-URL: Homepage, https://github.com/eric-langenberg/mosaic-map
Project-URL: Bug Tracker, https://github.com/eric-langenberg/mosaicmap/issues
Author-email: Eric Langenberg <eric-langenberg@users.noreply.github.com>
License-File: LICENSE
Classifier: License :: OSI Approved :: MIT License
Classifier: Operating System :: OS Independent
Classifier: Programming Language :: Python :: 3
Requires-Python: >=3.7
Requires-Dist: numpy>=1.20.0
Requires-Dist: pandas>=1.3.0
Requires-Dist: pillow>=9.0.0
Requires-Dist: squarify>=0.4.3
